Metadata-Version: 2.1
Name: TestMyFirstProjectLibrary
Version: 0.0.7.0
Summary: None
Author-email: akim.petbu@gmail.com
